src/timer_microsecond.sv
`timescale 1ns / 1ns

// Assert 'cycle' for one cycle every time a microsecond passes

module timer_microsecond#(
    parameter CLOCK_FREQUENCY_HZ=200000000,
    localparam MATCH=CLOCK_FREQUENCY_HZ/1000000,
    localparam CLOCK_COUNT_W    = $clog2(MATCH)
    )
    (
        input rst_n,    // active low rst_n
        input clk,
        output flag
    );

    /* verilator lint_off WIDTH */
    logic [CLOCK_COUNT_W-1:0] counter_r = MATCH;
    /* verilator lint_on WIDTH */

    assign flag = (counter_r == 0);

    always_ff @(posedge clk)
        counter_r <= (!rst_n) ? {CLOCK_COUNT_W{1'b1}} : counter_r + 1;

endmodule : timer_microsecond

src/timer_microseconds.sv
`timescale 1ns / 1ns

module timer_microseconds #(
    parameter CLOCK_FREQUENCY_HZ=200000000,
    parameter CLOCK_COUNT_W=32
    )
    (
        input wire                      rst_n, // active low reset
        input wire                      clk,
        input wire                      update_match,
        input wire [CLOCK_COUNT_W-1:0]  match,
        output wire                     done
    );

    logic [CLOCK_COUNT_W-1:0] counter_b;
    logic [CLOCK_COUNT_W-1:0] counter_r;

    logic done_b;
    logic done_r;

    logic microsecond_flag;

    timer_microsecond #(CLOCK_FREQUENCY_HZ) timer_microsecond_I
        (
        .rst_n(rst_n),
        .clk(clk),
        .flag(microsecond_flag)
        );

    always_comb
    begin
        counter_b               = counter_r;
        done_b                  = 0;
        if (update_match)
            // Update match
            counter_b           = match;
        else
        begin
            // Counting...
            if (counter_r != 0)
            begin
                if (microsecond_flag)
                    counter_b   = counter_r - 1;
                if (counter_b == 0)
                    done_b      = 1;
            end
            // Finished counting
            else
                done_b          = 0;
        end
    end

    assign done = done_r;

    always_ff @(posedge clk)
    begin
        if (!rst_n)
        begin
            counter_r       <= 0;
            done_r          <= 0;
        end
        else
        begin
            counter_r       <= counter_b;
            done_r          <= done_b;
        end
    end

endmodule : timer_microseconds

src/oled_power_on.sv
`timescale 1ns / 1ns

// Performs the OLED power on sequence for control signals

module oled_power_on #(
    parameter CLOCK_FREQUENCY_HZ=200000000,
    parameter DEBUG=0, // changes all timers to 10 us
    localparam CLOCK_COUNT_W=32,
    localparam WAIT_POWER_STABLE_US=20000,
    localparam WAIT_RESET_US=3
    )
    (
        input wire          rst_n,                  // active low reset
        input wire          sclk,                   // serial clock

        input wire          start,                  // high when valid SPI command received
        output wire         done,                   // assert high when power on sequence is done

        output wire         dc_c,                   // master out slave in
        output wire         res,                    // power reset
        output wire         vss_en,                 // vcc enable
        output wire         pmod_en                 // vdd logic voltage control
    );

    typedef enum
    {
        IDLE,
        START_SEQUENCE,
        SET_CONTROL,
        DISABLE_RESET,
        DISABLE_VCC,
        WAIT_POWER_STABLE,
        SET_RESET,
        WAIT_RESET,
        DONE
    } state;

    state state_b;
    state state_r;

    logic start_r;
    logic done_b;
    logic done_r;

    logic dc_c_b;
    logic dc_c_r;
    logic res_b;
    logic res_r;
    logic vss_en_b;
    logic vss_en_r;
    logic pmod_en_b;
    logic pmod_en_r;

    logic timer_update_match_b;
    logic [CLOCK_COUNT_W-1:0] timer_match_b;
    logic timer_done;


    timer_microseconds #(CLOCK_FREQUENCY_HZ, CLOCK_COUNT_W) timer_microseconds_I
    (
        .rst_n(rst_n),
        .clk(sclk),
        .update_match(timer_update_match_b),
        .match(timer_match_b),
        .done(timer_done)
    );

    always_comb
    begin
        if (start && !start_r)
            state_b         = START_SEQUENCE;
        else
        begin
            state_b         = state_r;
            // Outputs
            dc_c_b          = dc_c_r;
            res_b           = res_r;
            vss_en_b        = vss_en_r;
            pmod_en_b       = pmod_en_r;
            done_b          = done_r;
            // Timer
            timer_update_match_b   = 0;
            timer_match_b   = 0;
            case (state_r)
                START_SEQUENCE:
                begin
                    state_b = SET_CONTROL;
                    dc_c_b  = 0;
                end
                SET_CONTROL:
                begin
                    state_b = DISABLE_RESET;
                    res_b   = 1;
                end
                DISABLE_RESET:
                begin
                    state_b = DISABLE_VCC;
                    vss_en_b = 0;
                end
                DISABLE_VCC:
                begin
                    state_b = WAIT_POWER_STABLE;
                    pmod_en_b   = 1;
                    // Start a 20ms=20000us timer to wait for stable power
                    timer_update_match_b = 1;
                    timer_match_b = (DEBUG) ? 10 : WAIT_POWER_STABLE_US;
                end
                WAIT_POWER_STABLE:
                begin
                    if (timer_done)
                    begin
                        state_b = SET_RESET;
                        res_b = 0;
                        // Start a 3us timer to hold reset low
                        timer_update_match_b = 1;
                        timer_match_b = WAIT_RESET_US;
                    end
                end
                SET_RESET:
                begin
                    if (timer_done)
                    begin
                        state_b = WAIT_RESET;
                        res_b = 1;
                        // Start a 3us timer to wait for reset to complete
                        timer_update_match_b = 1;
                        timer_match_b = WAIT_RESET_US;
                    end
                end
                WAIT_RESET:
                begin
                    if (timer_done)
                    begin
                        state_b = DONE;
                        done_b  = 1;
                    end
                end
                DONE:
                begin
                    state_b = IDLE;
                    done_b  = 0;
                end
            endcase
        end
    end

    assign dc_c     = dc_c_r;
    assign res      = res_r;
    assign vss_en   = vss_en_r;
    assign pmod_en  = pmod_en_r;
    assign done     = done_r;

    always_ff @(posedge sclk)
    begin
        if (!rst_n)
        begin
            state_r         <= IDLE;

            start_r         <= 0;
            done_r          <= 0;

            dc_c_r          <= 0;
            res_r           <= 0;
            vss_en_r        <= 0;
            pmod_en_r       <= 0;
        end
        else begin
            state_r         <= state_b;

            start_r         <= start;
            done_r          <= done_b;

            dc_c_r          <= dc_c_b;
            res_r           <= res_b;
            vss_en_r        <= vss_en_b;
            pmod_en_r       <= pmod_en_b;
        end
    end

endmodule : oled_power_on

src/oled_controller.sv
`timescale 1ns / 1ns

/**
    - The display controller operates in SPI Mode 3 (clock idles on logic high, data is captured on the clock rising edge, and data is transferred on the clock falling edge) and with a minimum clock cycle time of 150 ns (as per table 21 of the SSD1331 datasheet). The embedded display only supports SPI write, so users will not be able to receive any information back from the display over SPI.

    - By driving and keeping the Chip Select (CS) line at a logic level low, users may send both commands and data streams to the display controller based on the state of the Data/Command (D/C) pin

    - The VCCEN control (pin 9) toggles the positive voltage supply to the screen itself and the PMODEN control (pin 10) toggles the power supply ground to the display. Users may turn off either one of these controls to reduce the power consumption of the Pmod OLEDrgb to approximately 200 nA.
*/

module oled_controller(
        input wire          rst_n,                   // active low reset
        input wire          sclk,                    // serial clock

        // verilator lint_off UNUSED

        input wire          command_valid,          // high when command_valid SPI command received
        input wire [7:0]    command,                // SPI command sent
        output wire         command_ready,          // assert high when command_ready for new SPI command

        /* verilator lint_off UNDRIVEN */
        output wire         cs,                     // chip select
        output wire         mosi,                   // master out slave in
        /* verilator lint_on UNDRIVEN */

        output wire         dc_c,                   // data/command control
        output wire         res,                    // power reset
        output wire         vss_en,                 // vcc enable
        output wire         pmod_en                 // vdd logic voltage control

        // verilator lint_on UNUSED
    );

    typedef enum
    {
        IDLE,
        POWER_ON,
        POWER_ON_SPI,
        READY,
        WAIT,
        POWER_OFF
    } state;

    state       state_b;
    state       state_r;

    logic command_ready_b;
    logic command_ready_r;

    logic start_pwr_on_b;
    logic pwr_on_done_b;

    oled_power_on #(200000000,1) oled_power_on_I (
        .rst_n(rst_n),
        .sclk(sclk),
        .start(start_pwr_on_b),
        .done(pwr_on_done_b),
        .dc_c(dc_c),
        .res(res),
        .vss_en(vss_en),
        .pmod_en(pmod_en)
    );

    logic start_pwr_on_spi_b;
    logic pwr_on_spi_done_b;

    assign command_ready            = command_ready_r;

    always_comb
    begin
        state_b                     = state_r;
        command_ready_b             = command_ready_r;
        start_pwr_on_b            = 0;
        start_pwr_on_spi_b          = 0;
        case (state_r)
            IDLE:
            begin
                state_b             = POWER_ON;
                start_pwr_on_b      = 1;
            end
            POWER_ON:
            begin
                start_pwr_on_b      = 0;
                if (pwr_on_done_b)
                begin
                    state_b         = POWER_ON_SPI;
                    start_pwr_on_spi_b = 1;
                end
            end
            POWER_ON_SPI:
            begin
                start_pwr_on_spi_b  = 0;
                if (pwr_on_spi_done_b)
                begin
                    state_b         = READY;
                    command_ready_b = 1;
                end
            end
            READY:
            begin
                if (command_valid)
                begin
                    state_b         = WAIT;
                    command_ready_b = 0;
                end
            end
            WAIT:
                state_b             = READY;
        endcase
    end

    always_ff @(posedge sclk)
    begin
        if (!rst_n)
        begin
            state_r                 <= IDLE;
            command_ready_r         <= 0;
        end
        else
        begin
            state_r                 <= state_b;
            command_ready_r         <= command_ready_b;
        end
    end

endmodule : oled_controller

src/waveform.vcd
$version Generated by VerilatedVcd $end
$date Fri Dec 29 20:33:28 2023
 $end
$timescale   1ns $end

 $scope module TOP $end
  $var wire  8 ? command [7:0] $end
  $var wire  1 @ command_ready $end
  $var wire  1 > command_valid $end
  $var wire  1 A cs $end
  $var wire  1 C dc_c $end
  $var wire  1 B mosi $end
  $var wire  1 F pmod_en $end
  $var wire  1 D res $end
  $var wire  1 < rst_n $end
  $var wire  1 = sclk $end
  $var wire  1 E vss_en $end
  $scope module oled_controller $end
   $var wire  8 ? command [7:0] $end
   $var wire  1 @ command_ready $end
   $var wire  1 H command_ready_b $end
   $var wire  1 $ command_ready_r $end
   $var wire  1 > command_valid $end
   $var wire  1 A cs $end
   $var wire  1 C dc_c $end
   $var wire  1 B mosi $end
   $var wire  1 F pmod_en $end
   $var wire  1 & pwr_on_done_b $end
   $var wire  1 I pwr_on_spi_done_b $end
   $var wire  1 D res $end
   $var wire  1 < rst_n $end
   $var wire  1 = sclk $end
   $var wire  1 % start_pwr_on_b $end
   $var wire  1 ' start_pwr_on_spi_b $end
   $var wire 32 G state_b [31:0] $end
   $var wire 32 # state_r [31:0] $end
   $var wire  1 E vss_en $end
   $scope module oled_power_on_I $end
    $var wire 32 L CLOCK_COUNT_W [31:0] $end
    $var wire 32 J CLOCK_FREQUENCY_HZ [31:0] $end
    $var wire 32 K DEBUG [31:0] $end
    $var wire 32 M WAIT_POWER_STABLE_US [31:0] $end
    $var wire 32 N WAIT_RESET_US [31:0] $end
    $var wire  1 C dc_c $end
    $var wire  1 , dc_c_b $end
    $var wire  1 - dc_c_r $end
    $var wire  1 & done $end
    $var wire  1 + done_b $end
    $var wire  1 & done_r $end
    $var wire  1 F pmod_en $end
    $var wire  1 2 pmod_en_b $end
    $var wire  1 3 pmod_en_r $end
    $var wire  1 D res $end
    $var wire  1 . res_b $end
    $var wire  1 / res_r $end
    $var wire  1 < rst_n $end
    $var wire  1 = sclk $end
    $var wire  1 % start $end
    $var wire  1 * start_r $end
    $var wire 32 ( state_b [31:0] $end
    $var wire 32 ) state_r [31:0] $end
    $var wire  1 6 timer_done $end
    $var wire 32 5 timer_match_b [31:0] $end
    $var wire  1 4 timer_update_match_b $end
    $var wire  1 E vss_en $end
    $var wire  1 0 vss_en_b $end
    $var wire  1 1 vss_en_r $end
    $scope module timer_microseconds_I $end
     $var wire 32 L CLOCK_COUNT_W [31:0] $end
     $var wire 32 J CLOCK_FREQUENCY_HZ [31:0] $end
     $var wire  1 = clk $end
     $var wire 32 7 counter_b [31:0] $end
     $var wire 32 8 counter_r [31:0] $end
     $var wire  1 6 done $end
     $var wire  1 9 done_b $end
     $var wire  1 6 done_r $end
     $var wire 32 5 match [31:0] $end
     $var wire  1 : microsecond_flag $end
     $var wire  1 < rst_n $end
     $var wire  1 4 update_match $end
     $scope module timer_microsecond_I $end
      $var wire 32 P CLOCK_COUNT_W [31:0] $end
      $var wire 32 J CLOCK_FREQUENCY_HZ [31:0] $end
      $var wire 32 O MATCH [31:0] $end
      $var wire  1 = clk $end
      $var wire  8 ; counter_r [7:0] $end
      $var wire  1 : flag $end
      $var wire  1 < rst_n $end
     $upscope $end
    $upscope $end
   $upscope $end
  $upscope $end
 $upscope $end
$enddefinitions $end


#0
b00000000000000000000000000000000 #
0$
1%
0&
0'
b00000000000000000000000000000001 (
b00000000000000000000000000000000 )
0*
0+
0,
0-
0.
0/
00
01
02
03
04
b00000000000000000000000000000000 5
06
b00000000000000000000000000000000 7
b00000000000000000000000000000000 8
09
0:
b11001000 ;
0<
1=
0>
b00000000 ?
0@
0A
0B
0C
0D
0E
0F
b00000000000000000000000000000001 G
0H
0I
b00001011111010111100001000000000 J
b00000000000000000000000000000001 K
b00000000000000000000000000100000 L
b00000000000000000100111000100000 M
b00000000000000000000000000000011 N
b00000000000000000000000011001000 O
b00000000000000000000000000001000 P
#1
0=
#2
b11111111 ;
1=
#3
0=
#4
1=
#5
0=
#6
1=
#7
0=
#8
b00000000000000000000000000000001 #
0%
b00000000000000000000000000000010 (
b00000000000000000000000000000001 )
1*
1:
b00000000 ;
1<
1=
#9
0=
#10
b00000000000000000000000000000011 (
b00000000000000000000000000000010 )
0*
1.
0:
b00000001 ;
1=
#11
0=
#12
b00000000000000000000000000000100 (
b00000000000000000000000000000011 )
1/
b00000010 ;
1=
1D
#13
0=
#14
b00000000000000000000000000000101 (
b00000000000000000000000000000100 )
12
14
b00000000000000000000000000001010 5
b00000000000000000000000000001010 7
b00000011 ;
1=
#15
0=
#16
b00000000000000000000000000000101 )
13
04
b00000000000000000000000000000000 5
b00000000000000000000000000001010 8
b00000100 ;
1=
1F
#17
0=
#18
b00000101 ;
1=
#19
0=
#20
b00000110 ;
1=
#21
0=
#22
b00000111 ;
1=
#23
0=
#24
b00001000 ;
1=
#25
0=
#26
b00001001 ;
1=
#27
0=
#28
b00001010 ;
1=
#29
0=
#30
b00001011 ;
1=
#31
0=
#32
b00001100 ;
1=
#33
0=
#34
b00001101 ;
1=
#35
0=
#36
b00001110 ;
1=
#37
0=
#38
b00001111 ;
1=
#39
0=
#40
b00010000 ;
1=
#41
0=
#42
b00010001 ;
1=
#43
0=
#44
b00010010 ;
1=
#45
0=
#46
b00010011 ;
1=
#47
0=
#48
b00010100 ;
1=
#49
0=
#50
b00010101 ;
1=
#51
0=
#52
b00010110 ;
1=
#53
0=
#54
b00010111 ;
1=
#55
0=
#56
b00011000 ;
1=
#57
0=
#58
b00011001 ;
1=
#59
0=
#60
b00011010 ;
1=
#61
0=
#62
b00011011 ;
1=
#63
0=
#64
b00011100 ;
1=
#65
0=
#66
b00011101 ;
1=
#67
0=
#68
b00011110 ;
1=
#69
0=
#70
b00011111 ;
1=
#71
0=
#72
b00100000 ;
1=
#73
0=
#74
b00100001 ;
1=
#75
0=
#76
b00100010 ;
1=
#77
0=
#78
b00100011 ;
1=
#79
0=
#80
b00100100 ;
1=
#81
0=
#82
b00100101 ;
1=
#83
0=
#84
b00100110 ;
1=
#85
0=
#86
b00100111 ;
1=
#87
0=
#88
b00101000 ;
1=
#89
0=
#90
b00101001 ;
1=
#91
0=
#92
b00101010 ;
1=
#93
0=
#94
b00101011 ;
1=
#95
0=
#96
b00101100 ;
1=
#97
0=
#98
b00101101 ;
1=
#99
0=
#100
b00101110 ;
1=
#101
0=
#102
b00101111 ;
1=
#103
0=
#104
b00110000 ;
1=
#105
0=
#106
b00110001 ;
1=
#107
0=
#108
b00110010 ;
1=
#109
0=
#110
b00110011 ;
1=
#111
0=
#112
b00110100 ;
1=
#113
0=
#114
b00110101 ;
1=
#115
0=
#116
b00110110 ;
1=
#117
0=
#118
b00110111 ;
1=
#119
0=
#120
b00111000 ;
1=
#121
0=
#122
b00111001 ;
1=
#123
0=
#124
b00111010 ;
1=
#125
0=
#126
b00111011 ;
1=
#127
0=
#128
b00111100 ;
1=
#129
0=
#130
b00111101 ;
1=
#131
0=
#132
b00111110 ;
1=
#133
0=
#134
b00111111 ;
1=
#135
0=
#136
b01000000 ;
1=
#137
0=
#138
b01000001 ;
1=
#139
0=
#140
b01000010 ;
1=
#141
0=
#142
b01000011 ;
1=
#143
0=
#144
b01000100 ;
1=
#145
0=
#146
b01000101 ;
1=
#147
0=
#148
b01000110 ;
1=
#149
0=
#150
b01000111 ;
1=
#151
0=
#152
b01001000 ;
1=
#153
0=
#154
b01001001 ;
1=
#155
0=
#156
b01001010 ;
1=
#157
0=
#158
b01001011 ;
1=
#159
0=
#160
b01001100 ;
1=
#161
0=
#162
b01001101 ;
1=
#163
0=
#164
b01001110 ;
1=
#165
0=
#166
b01001111 ;
1=
#167
0=
#168
b01010000 ;
1=
#169
0=
#170
b01010001 ;
1=
#171
0=
#172
b01010010 ;
1=
#173
0=
#174
b01010011 ;
1=
#175
0=
#176
b01010100 ;
1=
#177
0=
#178
b01010101 ;
1=
#179
0=
#180
b01010110 ;
1=
#181
0=
#182
b01010111 ;
1=
#183
0=
#184
b01011000 ;
1=
#185
0=
#186
b01011001 ;
1=
#187
0=
#188
b01011010 ;
1=
#189
0=
#190
b01011011 ;
1=
#191
0=
#192
b01011100 ;
1=
#193
0=
#194
b01011101 ;
1=
#195
0=
#196
b01011110 ;
1=
#197
0=
#198
b01011111 ;
1=
#199
0=
#200
b01100000 ;
1=
#201
0=
#202
b01100001 ;
1=
#203
0=
#204
b01100010 ;
1=
#205
0=
#206
b01100011 ;
1=
#207
0=
#208
b01100100 ;
1=
#209
0=
#210
b01100101 ;
1=
#211
0=
#212
b01100110 ;
1=
#213
0=
#214
b01100111 ;
1=
#215
0=
#216
b01101000 ;
1=
#217
0=
#218
b01101001 ;
1=
#219
0=
#220
b01101010 ;
1=
#221
0=
#222
b01101011 ;
1=
#223
0=
#224
b01101100 ;
1=
#225
0=
#226
b01101101 ;
1=
#227
0=
#228
b01101110 ;
1=
#229
0=
#230
b01101111 ;
1=
#231
0=
#232
b01110000 ;
1=
#233
0=
#234
b01110001 ;
1=
#235
0=
#236
b01110010 ;
1=
#237
0=
#238
b01110011 ;
1=
#239
0=
#240
b01110100 ;
1=
#241
0=
#242
b01110101 ;
1=
#243
0=
#244
b01110110 ;
1=
#245
0=
#246
b01110111 ;
1=
#247
0=
#248
b01111000 ;
1=
#249
0=
#250
b01111001 ;
1=
#251
0=
#252
b01111010 ;
1=
#253
0=
#254
b01111011 ;
1=
#255
0=
#256
b01111100 ;
1=
#257
0=
#258
b01111101 ;
1=
#259
0=
#260
b01111110 ;
1=
#261
0=
#262
b01111111 ;
1=
#263
0=
#264
b10000000 ;
1=
#265
0=
#266
b10000001 ;
1=
#267
0=
#268
b10000010 ;
1=
#269
0=
#270
b10000011 ;
1=
#271
0=
#272
b10000100 ;
1=
#273
0=
#274
b10000101 ;
1=
#275
0=
#276
b10000110 ;
1=
#277
0=
#278
b10000111 ;
1=
#279
0=
#280
b10001000 ;
1=
#281
0=
#282
b10001001 ;
1=
#283
0=
#284
b10001010 ;
1=
#285
0=
#286
b10001011 ;
1=
#287
0=
#288
b10001100 ;
1=
#289
0=
#290
b10001101 ;
1=
#291
0=
#292
b10001110 ;
1=
#293
0=
#294
b10001111 ;
1=
#295
0=
#296
b10010000 ;
1=
#297
0=
#298
b10010001 ;
1=
#299
0=
#300
b10010010 ;
1=
#301
0=
#302
b10010011 ;
1=
#303
0=
#304
b10010100 ;
1=
#305
0=
#306
b10010101 ;
1=
#307
0=
#308
b10010110 ;
1=
#309
0=
#310
b10010111 ;
1=
#311
0=
#312
b10011000 ;
1=
#313
0=
#314
b10011001 ;
1=
#315
0=
#316
b10011010 ;
1=
#317
0=
#318
b10011011 ;
1=
#319
0=
#320
b10011100 ;
1=
#321
0=
#322
b10011101 ;
1=
#323
0=
#324
b10011110 ;
1=
#325
0=
#326
b10011111 ;
1=
#327
0=
#328
b10100000 ;
1=
#329
0=
#330
b10100001 ;
1=
#331
0=
#332
b10100010 ;
1=
#333
0=
#334
b10100011 ;
1=
#335
0=
#336
b10100100 ;
1=
#337
0=
#338
b10100101 ;
1=
#339
0=
#340
b10100110 ;
1=
#341
0=
#342
b10100111 ;
1=
#343
0=
#344
b10101000 ;
1=
#345
0=
#346
b10101001 ;
1=
#347
0=
#348
b10101010 ;
1=
#349
0=
#350
b10101011 ;
1=
#351
0=
#352
b10101100 ;
1=
#353
0=
#354
b10101101 ;
1=
#355
0=
#356
b10101110 ;
1=
#357
0=
#358
b10101111 ;
1=
#359
0=
#360
b10110000 ;
1=
#361
0=
#362
b10110001 ;
1=
#363
0=
#364
b10110010 ;
1=
#365
0=
#366
b10110011 ;
1=
#367
0=
#368
b10110100 ;
1=
#369
0=
#370
b10110101 ;
1=
#371
0=
#372
b10110110 ;
1=
#373
0=
#374
b10110111 ;
1=
#375
0=
#376
b10111000 ;
1=
#377
0=
#378
b10111001 ;
1=
#379
0=
#380
b10111010 ;
1=
#381
0=
#382
b10111011 ;
1=
#383
0=
#384
b10111100 ;
1=
#385
0=
#386
b10111101 ;
1=
#387
0=
#388
b10111110 ;
1=
#389
0=
#390
b10111111 ;
1=
#391
0=
#392
b11000000 ;
1=
#393
0=
#394
b11000001 ;
1=
#395
0=
#396
b11000010 ;
1=
#397
0=
#398
b11000011 ;
1=
#399
0=
#400
b11000100 ;
1=
#401
0=
#402
b11000101 ;
1=
#403
0=
#404
b11000110 ;
1=
#405
0=
#406
b11000111 ;
1=
#407
0=
#408
b11001000 ;
1=
#409
0=
#410
b11001001 ;
1=
#411
0=
#412
b11001010 ;
1=
#413
0=
#414
b11001011 ;
1=
#415
0=
#416
b11001100 ;
1=
#417
0=
#418
b11001101 ;
1=
#419
0=
#420
b11001110 ;
1=
#421
0=
#422
b11001111 ;
1=
#423
0=
#424
b11010000 ;
1=
#425
0=
#426
b11010001 ;
1=
#427
0=
#428
b11010010 ;
1=
#429
0=
#430
b11010011 ;
1=
#431
0=
#432
b11010100 ;
1=
#433
0=
#434
b11010101 ;
1=
#435
0=
#436
b11010110 ;
1=
#437
0=
#438
b11010111 ;
1=
#439
0=
#440
b11011000 ;
1=
#441
0=
#442
b11011001 ;
1=
#443
0=
#444
b11011010 ;
1=
#445
0=
#446
b11011011 ;
1=
#447
0=
#448
b11011100 ;
1=
#449
0=
#450
b11011101 ;
1=
#451
0=
#452
b11011110 ;
1=
#453
0=
#454
b11011111 ;
1=
#455
0=
#456
b11100000 ;
1=
#457
0=
#458
b11100001 ;
1=
#459
0=
#460
b11100010 ;
1=
#461
0=
#462
b11100011 ;
1=
#463
0=
#464
b11100100 ;
1=
#465
0=
#466
b11100101 ;
1=
#467
0=
#468
b11100110 ;
1=
#469
0=
#470
b11100111 ;
1=
#471
0=
#472
b11101000 ;
1=
#473
0=
#474
b11101001 ;
1=
#475
0=
#476
b11101010 ;
1=
#477
0=
#478
b11101011 ;
1=
#479
0=
#480
b11101100 ;
1=
#481
0=
#482
b11101101 ;
1=
#483
0=
#484
b11101110 ;
1=
#485
0=
#486
b11101111 ;
1=
#487
0=
#488
b11110000 ;
1=
#489
0=
#490
b11110001 ;
1=
#491
0=
#492
b11110010 ;
1=
#493
0=
#494
b11110011 ;
1=
#495
0=
#496
b11110100 ;
1=
#497
0=
#498
b11110101 ;
1=
#499
0=
#500
b11110110 ;
1=
#501
0=
#502
b11110111 ;
1=
#503
0=
#504
b11111000 ;
1=
#505
0=
#506
b11111001 ;
1=
#507
0=
#508
b11111010 ;
1=
#509
0=
#510
b11111011 ;
1=
#511
0=
#512
b11111100 ;
1=
#513
0=
#514
b11111101 ;
1=
#515
0=
#516
b11111110 ;
1=
#517
0=
#518
b11111111 ;
1=
#519
0=
#520
b00000000000000000000000000001001 7
1:
b00000000 ;
1=
#521
0=
#522
b00000000000000000000000000001001 8
0:
b00000001 ;
1=
#523
0=
#524
b00000010 ;
1=
#525
0=
#526
b00000011 ;
1=
#527
0=
#528
b00000100 ;
1=
#529
0=
#530
b00000101 ;
1=
#531
0=
#532
b00000110 ;
1=
#533
0=
#534
b00000111 ;
1=
#535
0=
#536
b00001000 ;
1=
#537
0=
#538
b00001001 ;
1=
#539
0=
#540
b00001010 ;
1=
#541
0=
#542
b00001011 ;
1=
#543
0=
#544
b00001100 ;
1=
#545
0=
#546
b00001101 ;
1=
#547
0=
#548
b00001110 ;
1=
#549
0=
#550
b00001111 ;
1=
#551
0=
#552
b00010000 ;
1=
#553
0=
#554
b00010001 ;
1=
#555
0=
#556
b00010010 ;
1=
#557
0=
#558
b00010011 ;
1=
#559
0=
#560
b00010100 ;
1=
#561
0=
#562
b00010101 ;
1=
#563
0=
#564
b00010110 ;
1=
#565
0=
#566
b00010111 ;
1=
#567
0=
#568
b00011000 ;
1=
#569
0=
#570
b00011001 ;
1=
#571
0=
#572
b00011010 ;
1=
#573
0=
#574
b00011011 ;
1=
#575
0=
#576
b00011100 ;
1=
#577
0=
#578
b00011101 ;
1=
#579
0=
#580
b00011110 ;
1=
#581
0=
#582
b00011111 ;
1=
#583
0=
#584
b00100000 ;
1=
#585
0=
#586
b00100001 ;
1=
#587
0=
#588
b00100010 ;
1=
#589
0=
#590
b00100011 ;
1=
#591
0=
#592
b00100100 ;
1=
#593
0=
#594
b00100101 ;
1=
#595
0=
#596
b00100110 ;
1=
#597
0=
#598
b00100111 ;
1=
#599
0=
#600
b00101000 ;
1=
#601
0=
#602
b00101001 ;
1=
#603
0=
#604
b00101010 ;
1=
#605
0=
#606
b00101011 ;
1=
#607
0=
#608
b00101100 ;
1=
#609
0=
#610
b00101101 ;
1=
#611
0=
#612
b00101110 ;
1=
#613
0=
#614
b00101111 ;
1=
#615
0=
#616
b00110000 ;
1=
#617
0=
#618
b00110001 ;
1=
#619
0=
#620
b00110010 ;
1=
#621
0=
#622
b00110011 ;
1=
#623
0=
#624
b00110100 ;
1=
#625
0=
#626
b00110101 ;
1=
#627
0=
#628
b00110110 ;
1=
#629
0=
#630
b00110111 ;
1=
#631
0=
#632
b00111000 ;
1=
#633
0=
#634
b00111001 ;
1=
#635
0=
#636
b00111010 ;
1=
#637
0=
#638
b00111011 ;
1=
#639
0=
#640
b00111100 ;
1=
#641
0=
#642
b00111101 ;
1=
#643
0=
#644
b00111110 ;
1=
#645
0=
#646
b00111111 ;
1=
#647
0=
#648
b01000000 ;
1=
#649
0=
#650
b01000001 ;
1=
#651
0=
#652
b01000010 ;
1=
#653
0=
#654
b01000011 ;
1=
#655
0=
#656
b01000100 ;
1=
#657
0=
#658
b01000101 ;
1=
#659
0=
#660
b01000110 ;
1=
#661
0=
#662
b01000111 ;
1=
#663
0=
#664
b01001000 ;
1=
#665
0=
#666
b01001001 ;
1=
#667
0=
#668
b01001010 ;
1=
#669
0=
#670
b01001011 ;
1=
#671
0=
#672
b01001100 ;
1=
#673
0=
#674
b01001101 ;
1=
#675
0=
#676
b01001110 ;
1=
#677
0=
#678
b01001111 ;
1=
#679
0=
#680
b01010000 ;
1=
#681
0=
#682
b01010001 ;
1=
#683
0=
#684
b01010010 ;
1=
#685
0=
#686
b01010011 ;
1=
#687
0=
#688
b01010100 ;
1=
#689
0=
#690
b01010101 ;
1=
#691
0=
#692
b01010110 ;
1=
#693
0=
#694
b01010111 ;
1=
#695
0=
#696
b01011000 ;
1=
#697
0=
#698
b01011001 ;
1=
#699
0=
#700
b01011010 ;
1=
#701
0=
#702
b01011011 ;
1=
#703
0=
#704
b01011100 ;
1=
#705
0=
#706
b01011101 ;
1=
#707
0=
#708
b01011110 ;
1=
#709
0=
#710
b01011111 ;
1=
#711
0=
#712
b01100000 ;
1=
#713
0=
#714
b01100001 ;
1=
#715
0=
#716
b01100010 ;
1=
#717
0=
#718
b01100011 ;
1=
#719
0=
#720
b01100100 ;
1=
#721
0=
#722
b01100101 ;
1=
#723
0=
#724
b01100110 ;
1=
#725
0=
#726
b01100111 ;
1=
#727
0=
#728
b01101000 ;
1=
#729
0=
#730
b01101001 ;
1=
#731
0=
#732
b01101010 ;
1=
#733
0=
#734
b01101011 ;
1=
#735
0=
#736
b01101100 ;
1=
#737
0=
#738
b01101101 ;
1=
#739
0=
#740
b01101110 ;
1=
#741
0=
#742
b01101111 ;
1=
#743
0=
#744
b01110000 ;
1=
#745
0=
#746
b01110001 ;
1=
#747
0=
#748
b01110010 ;
1=
#749
0=
#750
b01110011 ;
1=
#751
0=
#752
b01110100 ;
1=
#753
0=
#754
b01110101 ;
1=
#755
0=
#756
b01110110 ;
1=
#757
0=
#758
b01110111 ;
1=
#759
0=
#760
b01111000 ;
1=
#761
0=
#762
b01111001 ;
1=
#763
0=
#764
b01111010 ;
1=
#765
0=
#766
b01111011 ;
1=
#767
0=
#768
b01111100 ;
1=
#769
0=
#770
b01111101 ;
1=
#771
0=
#772
b01111110 ;
1=
#773
0=
#774
b01111111 ;
1=
#775
0=
#776
b10000000 ;
1=
#777
0=
#778
b10000001 ;
1=
#779
0=
#780
b10000010 ;
1=
#781
0=
#782
b10000011 ;
1=
#783
0=
#784
b10000100 ;
1=
#785
0=
#786
b10000101 ;
1=
#787
0=
#788
b10000110 ;
1=
#789
0=
#790
b10000111 ;
1=
#791
0=
#792
b10001000 ;
1=
#793
0=
#794
b10001001 ;
1=
#795
0=
#796
b10001010 ;
1=
#797
0=
#798
b10001011 ;
1=
#799
0=
#800
b10001100 ;
1=
#801
0=
#802
b10001101 ;
1=
#803
0=
#804
b10001110 ;
1=
#805
0=
#806
b10001111 ;
1=
#807
0=
#808
b10010000 ;
1=
#809
0=
#810
b10010001 ;
1=
#811
0=
#812
b10010010 ;
1=
#813
0=
#814
b10010011 ;
1=
#815
0=
#816
b10010100 ;
1=
#817
0=
#818
b10010101 ;
1=
#819
0=
#820
b10010110 ;
1=
#821
0=
#822
b10010111 ;
1=
#823
0=
#824
b10011000 ;
1=
#825
0=
#826
b10011001 ;
1=
#827
0=
#828
b10011010 ;
1=
#829
0=
#830
b10011011 ;
1=
#831
0=
#832
b10011100 ;
1=
#833
0=
#834
b10011101 ;
1=
#835
0=
#836
b10011110 ;
1=
#837
0=
#838
b10011111 ;
1=
#839
0=
#840
b10100000 ;
1=
#841
0=
#842
b10100001 ;
1=
#843
0=
#844
b10100010 ;
1=
#845
0=
#846
b10100011 ;
1=
#847
0=
#848
b10100100 ;
1=
#849
0=
#850
b10100101 ;
1=
#851
0=
#852
b10100110 ;
1=
#853
0=
