src/fifo.sv
`timescale 1ns / 1ns

// FIFO implemented as dual port block ram with one clock
// Need to change this to correctly read mem initialisation

module fifo #(
    parameter DATA_WIDTH    = 8,
    parameter FIFO_DEPTH    = 1024,
    localparam FIFO_DEPTH_W = $clog2(FIFO_DEPTH)
    )
    (
    input wire                      rst_n,
    input wire                      clk,
    input wire                      write_en,
    input wire [DATA_WIDTH-1:0]     data_in,
    input wire                      read_en,
    output wire [DATA_WIDTH-1:0]    data_out,
    output wire                     full,
    output wire                     empty,
    output wire                     almost_full,
    output wire                     almost_empty
    );

    logic [DATA_WIDTH-1:0] ram [FIFO_DEPTH-1:0];
    logic [FIFO_DEPTH_W-1:0] write_ptr, read_ptr;

    assign full = (read_ptr == write_ptr);
    assign almost_full = (read_ptr == (write_ptr + 4));

    assign empty = (write_ptr == (read_ptr + 1));
    assign almost_empty = (write_ptr == (read_ptr + 4));

    assign data_out = ram[read_ptr];

    always_ff @(posedge clk)
    begin
        if (!rst_n)
        begin
            read_ptr            <= 0;
            write_ptr           <= 1;
            // PRELOAD RAM WITH POWER ON COMMANDS
            ram[0]              <= 8'hFD;
            ram[1]              <= 8'h12;
            ram[2]              <= 8'hAE;
            ram[3]              <= 8'hA0;
            ram[4]              <= 8'h72;
            ram[5]              <= 8'hA1;
            ram[6]              <= 8'h00;
            ram[7]              <= 8'hA2;
            ram[8]              <= 8'h00;
            ram[9]              <= 8'hA4;
            ram[10]             <= 8'hA8;
            ram[11]             <= 8'h3F;
            ram[12]             <= 8'hAD;
            ram[13]             <= 8'h8E;
            ram[14]             <= 8'hB0;
            ram[15]             <= 8'h0B;
            ram[16]             <= 8'hB1;
            ram[17]             <= 8'h31;
            ram[18]             <= 8'hB3;
            ram[19]             <= 8'hF0;
            ram[21]             <= 8'h8A;
            ram[22]             <= 8'h64;
            ram[23]             <= 8'h8B;
            ram[24]             <= 8'h78;
            ram[25]             <= 8'h8C;
            ram[26]             <= 8'h64;
            ram[27]             <= 8'hBB;
            ram[28]             <= 8'h3A;
            ram[29]             <= 8'hBE;
            ram[31]             <= 8'h3E;
            ram[32]             <= 8'h87;
            ram[33]             <= 8'h06;
            ram[34]             <= 8'h81;
            ram[35]             <= 8'h91;
            ram[36]             <= 8'h82;
            ram[37]             <= 8'h50;
            ram[38]             <= 8'h83;
            ram[39]             <= 8'h7D;
            ram[40]             <= 8'h2E;
            ram[40]             <= 8'h25;
            ram[40]             <= 8'h00;
            ram[40]             <= 8'h00;
            ram[40]             <= 8'h5F;
            ram[40]             <= 8'h3F;
            ram[40]             <= 8'hAF;
        end
        else
        begin
            if (write_en)
            begin
                ram[write_ptr] <= data_in;
                write_ptr      <= write_ptr + 1;
            end
            if (read_en)
            begin
                read_ptr       <= read_ptr + 1;
            end
        end
    end

endmodule : fifo

src/oled_serial_buffer.sv
`timescale 1ns / 1ns

// Discards commands if the buffer is full (violates handshake)

module oled_serial_buffer #(
    parameter BUFFER_MAX = 1024,        // maximum number of serial commands that can be buffered
    parameter COMMAND_W  = 8            // bit width of serial commands
    )
    (
        input wire                  rst_n,
        input wire                  clk,
        input wire [COMMAND_W-1:0]  command_in,
        input wire                  command_in_valid,
        input wire                  read_command,

        output wire [COMMAND_W-1:0] command_out,
        output wire                 commands_empty,
        output wire                 commands_full
    );

    logic full;
    logic empty;

    logic read_en_b;
    logic write_en_b;

    assign commands_empty   = empty;
    assign commands_full    = full;

    assign write_en_b       = command_in_valid && !full;
    assign read_en_b        = read_command && !empty;

    fifo #(COMMAND_W, BUFFER_MAX) fifo_I
    (
        .rst_n(rst_n),
        .clk(clk),
        .write_en(write_en_b),
        .data_in(command_in),
        .read_en(read_en_b),
        .data_out(command_out),
        .full(full),
        .empty(empty),
        /* verilator lint_off PINCONNECTEMPTY */
        .almost_full(),
        .almost_empty()
        /* verilator lint_on PINCONNECTEMPTY */
    );

endmodule : oled_serial_buffer

src/timer_microsecond.sv
`timescale 1ns / 1ns

// Assert 'cycle' for one cycle every time a microsecond passes

module timer_microsecond#(
    parameter CLOCK_FREQUENCY_HZ    = 200000000,
    localparam MATCH                = CLOCK_FREQUENCY_HZ/1000000,
    localparam CLOCK_COUNT_W        = $clog2(MATCH)
    )
    (
        input rst_n,    // active low rst_n
        input clk,
        output flag
    );

    /* verilator lint_off WIDTH */
    logic [CLOCK_COUNT_W-1:0] counter_r = MATCH;
    /* verilator lint_on WIDTH */

    assign flag = (counter_r == 0);

    always_ff @(posedge clk)
        counter_r <= (!rst_n) ? {CLOCK_COUNT_W{1'b1}} : counter_r + 1;

endmodule : timer_microsecond

src/timer_microseconds.sv
`timescale 1ns / 1ns

module timer_microseconds #(
    parameter CLOCK_FREQUENCY_HZ    = 200000000,
    parameter CLOCK_COUNT_W         = 32
    )
    (
        input wire                      rst_n, // active low reset
        input wire                      clk,
        input wire                      update_match,
        input wire [CLOCK_COUNT_W-1:0]  match,
        output wire                     done
    );

    logic [CLOCK_COUNT_W-1:0] counter_b;
    logic [CLOCK_COUNT_W-1:0] counter_r;

    logic done_b;
    logic done_r;

    logic microsecond_flag;

    timer_microsecond #(CLOCK_FREQUENCY_HZ) timer_microsecond_I
        (
        .rst_n(rst_n),
        .clk(clk),
        .flag(microsecond_flag)
        );

    always_comb
    begin
        counter_b               = counter_r;
        done_b                  = 0;
        if (update_match)
            // Update match
            counter_b           = match;
        else
        begin
            // Counting...
            if (counter_r != 0)
            begin
                if (microsecond_flag)
                    counter_b   = counter_r - 1;
                if (counter_b == 0)
                    done_b      = 1;
            end
            // Finished counting
            else
                done_b          = 0;
        end
    end

    assign done = done_r;

    always_ff @(posedge clk)
    begin
        if (!rst_n)
        begin
            counter_r       <= 0;
            done_r          <= 0;
        end
        else
        begin
            counter_r       <= counter_b;
            done_r          <= done_b;
        end
    end

endmodule : timer_microseconds

src/oled_power_on.sv
`timescale 1ns / 1ns

// Performs the OLED power on sequence for control signals

module oled_power_on #(
    parameter CLOCK_FREQUENCY_HZ    = 200000000,
    parameter DEBUG                 = 0, // changes all timers to 10 us
    localparam CLOCK_COUNT_W        = 32,
    localparam WAIT_POWER_STABLE_US = 20000,
    localparam WAIT_RESET_US        = 3
    )
    (
        input wire          rst_n,                  // active low reset
        input wire          sclk,                   // serial clock

        input wire          start,                  // high when valid SPI command received
        output wire         done,                   // assert high when power on sequence is done

        output wire         dc_c,                   // master out slave in
        output wire         res,                    // power reset
        output wire         vss_en,                 // vcc enable
        output wire         pmod_en                 // vdd logic voltage control
    );

    typedef enum
    {
        IDLE,
        START_SEQUENCE,
        SET_CONTROL,
        DISABLE_RESET,
        DISABLE_VCC,
        WAIT_POWER_STABLE,
        SET_RESET,
        WAIT_RESET,
        DONE
    } state;

    state state_b;
    state state_r;

    logic start_r;
    logic done_b;
    logic done_r;

    logic dc_c_b;
    logic dc_c_r;
    logic res_b;
    logic res_r;
    logic vss_en_b;
    logic vss_en_r;
    logic pmod_en_b;
    logic pmod_en_r;

    logic timer_update_match_b;
    logic [CLOCK_COUNT_W-1:0] timer_match_b;
    logic timer_done;


    timer_microseconds #(CLOCK_FREQUENCY_HZ, CLOCK_COUNT_W) timer_microseconds_I
    (
        .rst_n(rst_n),
        .clk(sclk),
        .update_match(timer_update_match_b),
        .match(timer_match_b),
        .done(timer_done)
    );

    always_comb
    begin
        if (start && !start_r)
            state_b         = START_SEQUENCE;
        else
        begin
            state_b         = state_r;
            // Outputs
            dc_c_b          = dc_c_r;
            res_b           = res_r;
            vss_en_b        = vss_en_r;
            pmod_en_b       = pmod_en_r;
            done_b          = done_r;
            // Timer
            timer_update_match_b   = 0;
            timer_match_b   = 0;
            case (state_r)
                START_SEQUENCE:
                begin
                    state_b = SET_CONTROL;
                    dc_c_b  = 0;
                end
                SET_CONTROL:
                begin
                    state_b = DISABLE_RESET;
                    res_b   = 1;
                end
                DISABLE_RESET:
                begin
                    state_b = DISABLE_VCC;
                    vss_en_b = 0;
                end
                DISABLE_VCC:
                begin
                    state_b = WAIT_POWER_STABLE;
                    pmod_en_b   = 1;
                    // Start a 20ms=20000us timer to wait for stable power
                    timer_update_match_b = 1;
                    timer_match_b = (DEBUG) ? 10 : WAIT_POWER_STABLE_US;
                end
                WAIT_POWER_STABLE:
                begin
                    if (timer_done)
                    begin
                        state_b = SET_RESET;
                        res_b = 0;
                        // Start a 3us timer to hold reset low
                        timer_update_match_b = 1;
                        timer_match_b = WAIT_RESET_US;
                    end
                end
                SET_RESET:
                begin
                    if (timer_done)
                    begin
                        state_b = WAIT_RESET;
                        res_b = 1;
                        // Start a 3us timer to wait for reset to complete
                        timer_update_match_b = 1;
                        timer_match_b = WAIT_RESET_US;
                    end
                end
                WAIT_RESET:
                begin
                    if (timer_done)
                    begin
                        state_b = DONE;
                        done_b  = 1;
                    end
                end
                DONE:
                begin
                    state_b = IDLE;
                    done_b  = 0;
                end
            endcase
        end
    end

    assign dc_c     = dc_c_r;
    assign res      = res_r;
    assign vss_en   = vss_en_r;
    assign pmod_en  = pmod_en_r;
    assign done     = done_r;

    always_ff @(posedge sclk)
    begin
        if (!rst_n)
        begin
            state_r         <= IDLE;

            start_r         <= 0;
            done_r          <= 0;

            dc_c_r          <= 0;
            res_r           <= 0;
            vss_en_r        <= 0;
            pmod_en_r       <= 0;
        end
        else begin
            state_r         <= state_b;

            start_r         <= start;
            done_r          <= done_b;

            dc_c_r          <= dc_c_b;
            res_r           <= res_b;
            vss_en_r        <= vss_en_b;
            pmod_en_r       <= pmod_en_b;
        end
    end

endmodule : oled_power_on

src/oled_controller.sv
`timescale 1ns / 1ns

/**
    - The display controller operates in SPI Mode 3 (clock idles on logic high, data is captured on the clock rising edge, and data is transferred on the clock falling edge) and with a minimum clock cycle time of 150 ns (as per table 21 of the SSD1331 datasheet). The embedded display only supports SPI write, so users will not be able to receive any information back from the display over SPI.

    - By driving and keeping the Chip Select (CS) line at a logic level low, users may send both commands and data streams to the display controller based on the state of the Data/Command (D/C) pin

    - The VCCEN control (pin 9) toggles the positive voltage supply to the screen itself and the PMODEN control (pin 10) toggles the power supply ground to the display. Users may turn off either one of these controls to reduce the power consumption of the Pmod OLEDrgb to approximately 200 nA.
*/

module oled_controller(
        input wire          rst_n,                   // active low reset
        input wire          sclk,                    // serial clock

        // verilator lint_off UNUSED

        input wire          command_valid,          // high when command_valid SPI command received
        input wire [7:0]    command,                // SPI command sent
        output wire         command_ready,          // assert high when command_ready for new SPI command

        /* verilator lint_off UNDRIVEN */
        output wire         cs,                     // chip select
        output wire         mosi,                   // master out slave in
        /* verilator lint_on UNDRIVEN */

        output wire         dc_c,                   // data/command control
        output wire         res,                    // power reset
        output wire         vss_en,                 // vcc enable
        output wire         pmod_en                 // vdd logic voltage control

        // verilator lint_on UNUSED
    );

    typedef enum
    {
        IDLE,
        POWER_ON,
        POWER_ON_SPI,
        READY,
        WAIT,
        POWER_OFF
    } state;

    state       state_b;
    state       state_r;

    logic       command_ready_b;
    logic       command_ready_r;

    logic       start_pwr_on_b;
    logic       pwr_on_done_b;

    oled_power_on #(200000000,1) oled_power_on_I (
        .rst_n(rst_n),
        .sclk(sclk),
        .start(start_pwr_on_b),
        .done(pwr_on_done_b),
        .dc_c(dc_c),
        .res(res),
        .vss_en(vss_en),
        .pmod_en(pmod_en)
    );

    logic       start_pwr_on_spi_b;
    logic       pwr_on_spi_done_b;

    logic       commands_empty;
    logic       commands_full;

    logic       read_command_b;

    logic [7:0] command_in_b;
    logic       command_in_valid_b;

    logic [7:0] command_out_b;
    logic       command_out_valid_b;

    oled_serial_buffer #(1024, 8) oled_serial_buffer_I (
        .rst_n(rst_n),
        .clk(sclk),
        .command_in(command_in_b),
        .command_in_valid(command_in_valid_b),
        .read_command(read_command_b),
        .command_out(command_out_b),
        .commands_empty(commands_empty),
        .commands_full(commands_full)
    );

    assign command_out_valid_b = !commands_empty && read_command_b;

    assign command_ready            = command_ready_r;

    always_comb
    begin
        state_b                     = state_r;
        command_ready_b             = command_ready_r;
        start_pwr_on_b              = 0;
        start_pwr_on_spi_b          = 0;
        read_command_b              = 0;
        case (state_r)
            IDLE:
            begin
                state_b             = POWER_ON;
                start_pwr_on_b      = 1;
            end
            POWER_ON:
            begin
                start_pwr_on_b      = 0;
                if (pwr_on_done_b)
                begin
                    state_b         = POWER_ON_SPI;
                    start_pwr_on_spi_b = 1;
                end
            end
            POWER_ON_SPI:
            begin
                start_pwr_on_spi_b  = 0;
                read_command_b      = 1;
                if (pwr_on_spi_done_b)
                begin
                    state_b         = READY;
                    command_ready_b = 1;
                end
            end
            READY:
            begin
                if (command_valid)
                begin
                    state_b         = WAIT;
                    command_ready_b = 0;
                end
            end
            WAIT:
                state_b             = READY;
        endcase
    end

    always_ff @(posedge sclk)
    begin
        if (!rst_n)
        begin
            state_r                 <= IDLE;
            command_ready_r         <= 0;
        end
        else
        begin
            state_r                 <= state_b;
            command_ready_r         <= command_ready_b;
        end
    end

endmodule : oled_controller

src/waveform.vcd
$version Generated by VerilatedVcd $end
$date Fri Dec 29 22:15:43 2023
 $end
$timescale   1ns $end

 $scope module TOP $end
  $var wire  8 J command [7:0] $end
  $var wire  1 K command_ready $end
  $var wire  1 I command_valid $end
  $var wire  1 L cs $end
  $var wire  1 N dc_c $end
  $var wire  1 M mosi $end
  $var wire  1 Q pmod_en $end
  $var wire  1 O res $end
  $var wire  1 G rst_n $end
  $var wire  1 H sclk $end
  $var wire  1 P vss_en $end
  $scope module oled_controller $end
   $var wire  8 J command [7:0] $end
   $var wire  8 U command_in_b [7:0] $end
   $var wire  1 V command_in_valid_b $end
   $var wire  8 + command_out_b [7:0] $end
   $var wire  1 , command_out_valid_b $end
   $var wire  1 K command_ready $end
   $var wire  1 S command_ready_b $end
   $var wire  1 $ command_ready_r $end
   $var wire  1 I command_valid $end
   $var wire  1 ( commands_empty $end
   $var wire  1 ) commands_full $end
   $var wire  1 L cs $end
   $var wire  1 N dc_c $end
   $var wire  1 M mosi $end
   $var wire  1 Q pmod_en $end
   $var wire  1 & pwr_on_done_b $end
   $var wire  1 T pwr_on_spi_done_b $end
   $var wire  1 * read_command_b $end
   $var wire  1 O res $end
   $var wire  1 G rst_n $end
   $var wire  1 H sclk $end
   $var wire  1 % start_pwr_on_b $end
   $var wire  1 ' start_pwr_on_spi_b $end
   $var wire 32 R state_b [31:0] $end
   $var wire 32 # state_r [31:0] $end
   $var wire  1 P vss_en $end
   $scope module oled_power_on_I $end
    $var wire 32 Y CLOCK_COUNT_W [31:0] $end
    $var wire 32 W CLOCK_FREQUENCY_HZ [31:0] $end
    $var wire 32 X DEBUG [31:0] $end
    $var wire 32 Z WAIT_POWER_STABLE_US [31:0] $end
    $var wire 32 [ WAIT_RESET_US [31:0] $end
    $var wire  1 N dc_c $end
    $var wire  1 1 dc_c_b $end
    $var wire  1 2 dc_c_r $end
    $var wire  1 & done $end
    $var wire  1 0 done_b $end
    $var wire  1 & done_r $end
    $var wire  1 Q pmod_en $end
    $var wire  1 7 pmod_en_b $end
    $var wire  1 8 pmod_en_r $end
    $var wire  1 O res $end
    $var wire  1 3 res_b $end
    $var wire  1 4 res_r $end
    $var wire  1 G rst_n $end
    $var wire  1 H sclk $end
    $var wire  1 % start $end
    $var wire  1 / start_r $end
    $var wire 32 - state_b [31:0] $end
    $var wire 32 . state_r [31:0] $end
    $var wire  1 ; timer_done $end
    $var wire 32 : timer_match_b [31:0] $end
    $var wire  1 9 timer_update_match_b $end
    $var wire  1 P vss_en $end
    $var wire  1 5 vss_en_b $end
    $var wire  1 6 vss_en_r $end
    $scope module timer_microseconds_I $end
     $var wire 32 Y CLOCK_COUNT_W [31:0] $end
     $var wire 32 W CLOCK_FREQUENCY_HZ [31:0] $end
     $var wire  1 H clk $end
     $var wire 32 < counter_b [31:0] $end
     $var wire 32 = counter_r [31:0] $end
     $var wire  1 ; done $end
     $var wire  1 > done_b $end
     $var wire  1 ; done_r $end
     $var wire 32 : match [31:0] $end
     $var wire  1 ? microsecond_flag $end
     $var wire  1 G rst_n $end
     $var wire  1 9 update_match $end
     $scope module timer_microsecond_I $end
      $var wire 32 ] CLOCK_COUNT_W [31:0] $end
      $var wire 32 W CLOCK_FREQUENCY_HZ [31:0] $end
      $var wire 32 \ MATCH [31:0] $end
      $var wire  1 H clk $end
      $var wire  8 @ counter_r [7:0] $end
      $var wire  1 ? flag $end
      $var wire  1 G rst_n $end
     $upscope $end
    $upscope $end
   $upscope $end
   $scope module oled_serial_buffer_I $end
    $var wire 32 ^ BUFFER_MAX [31:0] $end
    $var wire 32 ] COMMAND_W [31:0] $end
    $var wire  1 H clk $end
    $var wire  8 U command_in [7:0] $end
    $var wire  1 V command_in_valid $end
    $var wire  8 + command_out [7:0] $end
    $var wire  1 ( commands_empty $end
    $var wire  1 ) commands_full $end
    $var wire  1 ( empty $end
    $var wire  1 ) full $end
    $var wire  1 * read_command $end
    $var wire  1 A read_en_b $end
    $var wire  1 G rst_n $end
    $var wire  1 B write_en_b $end
    $scope module fifo_I $end
     $var wire 32 ] DATA_WIDTH [31:0] $end
     $var wire 32 ^ FIFO_DEPTH [31:0] $end
     $var wire 32 _ FIFO_DEPTH_W [31:0] $end
     $var wire  1 D almost_empty $end
     $var wire  1 C almost_full $end
     $var wire  1 H clk $end
     $var wire  8 U data_in [7:0] $end
     $var wire  8 + data_out [7:0] $end
     $var wire  1 ( empty $end
     $var wire  1 ) full $end
     $var wire  1 A read_en $end
     $var wire 10 F read_ptr [9:0] $end
     $var wire  1 G rst_n $end
     $var wire  1 B write_en $end
     $var wire 10 E write_ptr [9:0] $end
    $upscope $end
   $upscope $end
  $upscope $end
 $upscope $end
$enddefinitions $end


#0
b00000000000000000000000000000000 #
0$
1%
0&
0'
0(
1)
0*
b00000000 +
0,
b00000000000000000000000000000001 -
b00000000000000000000000000000000 .
0/
00
01
02
03
04
05
06
07
08
09
b00000000000000000000000000000000 :
0;
b00000000000000000000000000000000 <
b00000000000000000000000000000000 =
0>
0?
b11001000 @
0A
0B
0C
0D
b0000000000 E
b0000000000 F
0G
1H
0I
b00000000 J
0K
0L
0M
0N
0O
0P
0Q
b00000000000000000000000000000001 R
0S
0T
b00000000 U
0V
b00001011111010111100001000000000 W
b00000000000000000000000000000001 X
b00000000000000000000000000100000 Y
b00000000000000000100111000100000 Z
b00000000000000000000000000000011 [
b00000000000000000000000011001000 \
b00000000000000000000000000001000 ]
b00000000000000000000010000000000 ^
b00000000000000000000000000001010 _
#1
0H
#2
1(
0)
b11111101 +
b11111111 @
b0000000001 E
1H
#3
0H
#4
1H
#5
0H
#6
1H
#7
0H
#8
b00000000000000000000000000000001 #
0%
b00000000000000000000000000000010 -
b00000000000000000000000000000001 .
1/
1?
b00000000 @
1G
1H
#9
0H
#10
b00000000000000000000000000000011 -
b00000000000000000000000000000010 .
0/
13
0?
b00000001 @
1H
#11
0H
#12
b00000000000000000000000000000100 -
b00000000000000000000000000000011 .
14
b00000010 @
1H
1O
#13
0H
#14
b00000000000000000000000000000101 -
b00000000000000000000000000000100 .
17
19
b00000000000000000000000000001010 :
b00000000000000000000000000001010 <
b00000011 @
1H
#15
0H
#16
b00000000000000000000000000000101 .
18
09
b00000000000000000000000000000000 :
b00000000000000000000000000001010 =
b00000100 @
1H
1Q
#17
0H
#18
b00000101 @
1H
#19
0H
#20
b00000110 @
1H
#21
0H
#22
b00000111 @
1H
#23
0H
#24
b00001000 @
1H
#25
0H
#26
b00001001 @
1H
#27
0H
#28
b00001010 @
1H
#29
0H
#30
b00001011 @
1H
#31
0H
#32
b00001100 @
1H
#33
0H
#34
b00001101 @
1H
#35
0H
#36
b00001110 @
1H
#37
0H
#38
b00001111 @
1H
#39
0H
#40
b00010000 @
1H
#41
0H
#42
b00010001 @
1H
#43
0H
#44
b00010010 @
1H
#45
0H
#46
b00010011 @
1H
#47
0H
#48
b00010100 @
1H
#49
0H
#50
b00010101 @
1H
#51
0H
#52
b00010110 @
1H
#53
0H
#54
b00010111 @
1H
#55
0H
#56
b00011000 @
1H
#57
0H
#58
b00011001 @
1H
#59
0H
#60
b00011010 @
1H
#61
0H
#62
b00011011 @
1H
#63
0H
#64
b00011100 @
1H
#65
0H
#66
b00011101 @
1H
#67
0H
#68
b00011110 @
1H
#69
0H
#70
b00011111 @
1H
#71
0H
#72
b00100000 @
1H
#73
0H
#74
b00100001 @
1H
#75
0H
#76
b00100010 @
1H
#77
0H
#78
b00100011 @
1H
#79
0H
#80
b00100100 @
1H
#81
0H
#82
b00100101 @
1H
#83
0H
#84
b00100110 @
1H
#85
0H
#86
b00100111 @
1H
#87
0H
#88
b00101000 @
1H
#89
0H
#90
b00101001 @
1H
#91
0H
#92
b00101010 @
1H
#93
0H
#94
b00101011 @
1H
#95
0H
#96
b00101100 @
1H
#97
0H
#98
b00101101 @
1H
#99
0H
#100
b00101110 @
1H
#101
0H
#102
b00101111 @
1H
#103
0H
#104
b00110000 @
1H
#105
0H
#106
b00110001 @
1H
#107
0H
#108
b00110010 @
1H
#109
0H
#110
b00110011 @
1H
#111
0H
#112
b00110100 @
1H
#113
0H
#114
b00110101 @
1H
#115
0H
#116
b00110110 @
1H
#117
0H
#118
b00110111 @
1H
#119
0H
#120
b00111000 @
1H
#121
0H
#122
b00111001 @
1H
#123
0H
#124
b00111010 @
1H
#125
0H
#126
b00111011 @
1H
#127
0H
#128
b00111100 @
1H
#129
0H
#130
b00111101 @
1H
#131
0H
#132
b00111110 @
1H
#133
0H
#134
b00111111 @
1H
#135
0H
#136
b01000000 @
1H
#137
0H
#138
b01000001 @
1H
#139
0H
#140
b01000010 @
1H
#141
0H
#142
b01000011 @
1H
#143
0H
#144
b01000100 @
1H
#145
0H
#146
b01000101 @
1H
#147
0H
#148
b01000110 @
1H
#149
0H
#150
b01000111 @
1H
#151
0H
#152
b01001000 @
1H
#153
0H
#154
b01001001 @
1H
#155
0H
#156
b01001010 @
1H
#157
0H
#158
b01001011 @
1H
#159
0H
#160
b01001100 @
1H
#161
0H
#162
b01001101 @
1H
#163
0H
#164
b01001110 @
1H
#165
0H
#166
b01001111 @
1H
#167
0H
#168
b01010000 @
1H
#169
0H
#170
b01010001 @
1H
#171
0H
#172
b01010010 @
1H
#173
0H
#174
b01010011 @
1H
#175
0H
#176
b01010100 @
1H
#177
0H
#178
b01010101 @
1H
#179
0H
#180
b01010110 @
1H
#181
0H
#182
b01010111 @
1H
#183
0H
#184
b01011000 @
1H
#185
0H
#186
b01011001 @
1H
#187
0H
#188
b01011010 @
1H
#189
0H
#190
b01011011 @
1H
#191
0H
#192
b01011100 @
1H
#193
0H
#194
b01011101 @
1H
#195
0H
#196
b01011110 @
1H
#197
0H
#198
b01011111 @
1H
#199
0H
#200
b01100000 @
1H
#201
0H
#202
b01100001 @
1H
#203
0H
#204
b01100010 @
1H
#205
0H
#206
b01100011 @
1H
#207
0H
#208
b01100100 @
1H
#209
0H
#210
b01100101 @
1H
#211
0H
#212
b01100110 @
1H
#213
0H
#214
b01100111 @
1H
#215
0H
#216
b01101000 @
1H
#217
0H
#218
b01101001 @
1H
#219
0H
#220
b01101010 @
1H
#221
0H
#222
b01101011 @
1H
#223
0H
#224
b01101100 @
1H
#225
0H
#226
b01101101 @
1H
#227
0H
#228
b01101110 @
1H
#229
0H
#230
b01101111 @
1H
#231
0H
#232
b01110000 @
1H
#233
0H
#234
b01110001 @
1H
#235
0H
#236
b01110010 @
1H
#237
0H
#238
b01110011 @
1H
#239
0H
#240
b01110100 @
1H
#241
0H
#242
b01110101 @
1H
#243
0H
#244
b01110110 @
1H
#245
0H
#246
b01110111 @
1H
#247
0H
#248
b01111000 @
1H
#249
0H
#250
b01111001 @
1H
#251
0H
#252
b01111010 @
1H
#253
0H
#254
b01111011 @
1H
#255
0H
#256
b01111100 @
1H
#257
0H
#258
b01111101 @
1H
#259
0H
#260
b01111110 @
1H
#261
0H
#262
b01111111 @
1H
#263
0H
#264
b10000000 @
1H
#265
0H
#266
b10000001 @
1H
#267
0H
#268
b10000010 @
1H
#269
0H
#270
b10000011 @
1H
#271
0H
#272
b10000100 @
1H
#273
0H
#274
b10000101 @
1H
#275
0H
#276
b10000110 @
1H
#277
0H
#278
b10000111 @
1H
#279
0H
#280
b10001000 @
1H
#281
0H
#282
b10001001 @
1H
#283
0H
#284
b10001010 @
1H
#285
0H
#286
b10001011 @
1H
#287
0H
#288
b10001100 @
1H
#289
0H
#290
b10001101 @
1H
#291
0H
#292
b10001110 @
1H
#293
0H
#294
b10001111 @
1H
#295
0H
#296
b10010000 @
1H
#297
0H
#298
b10010001 @
1H
#299
0H
#300
b10010010 @
1H
#301
0H
#302
b10010011 @
1H
#303
0H
#304
b10010100 @
1H
#305
0H
#306
b10010101 @
1H
#307
0H
#308
b10010110 @
1H
#309
0H
#310
b10010111 @
1H
#311
0H
#312
b10011000 @
1H
#313
0H
#314
b10011001 @
1H
#315
0H
#316
b10011010 @
1H
#317
0H
#318
b10011011 @
1H
#319
0H
#320
b10011100 @
1H
#321
0H
#322
b10011101 @
1H
#323
0H
#324
b10011110 @
1H
#325
0H
#326
b10011111 @
1H
#327
0H
#328
b10100000 @
1H
#329
0H
#330
b10100001 @
1H
#331
0H
#332
b10100010 @
1H
#333
0H
#334
b10100011 @
1H
#335
0H
#336
b10100100 @
1H
#337
0H
#338
b10100101 @
1H
#339
0H
#340
b10100110 @
1H
#341
0H
#342
b10100111 @
1H
#343
0H
#344
b10101000 @
1H
#345
0H
#346
b10101001 @
1H
#347
0H
#348
b10101010 @
1H
#349
0H
#350
b10101011 @
1H
#351
0H
#352
b10101100 @
1H
#353
0H
#354
b10101101 @
1H
#355
0H
#356
b10101110 @
1H
#357
0H
#358
b10101111 @
1H
#359
0H
#360
b10110000 @
1H
#361
0H
#362
b10110001 @
1H
#363
0H
#364
b10110010 @
1H
#365
0H
#366
b10110011 @
1H
#367
0H
#368
b10110100 @
1H
#369
0H
#370
b10110101 @
1H
#371
0H
#372
b10110110 @
1H
#373
0H
#374
b10110111 @
1H
#375
0H
#376
b10111000 @
1H
#377
0H
#378
b10111001 @
1H
#379
0H
#380
b10111010 @
1H
#381
0H
#382
b10111011 @
1H
#383
0H
#384
b10111100 @
1H
#385
0H
#386
b10111101 @
1H
#387
0H
#388
b10111110 @
1H
#389
0H
#390
b10111111 @
1H
#391
0H
#392
b11000000 @
1H
#393
0H
#394
b11000001 @
1H
#395
0H
#396
b11000010 @
1H
#397
0H
#398
b11000011 @
1H
#399
0H
#400
b11000100 @
1H
#401
0H
#402
b11000101 @
1H
#403
0H
#404
b11000110 @
1H
#405
0H
#406
b11000111 @
1H
#407
0H
#408
b11001000 @
1H
#409
0H
#410
b11001001 @
1H
#411
0H
#412
b11001010 @
1H
#413
0H
#414
b11001011 @
1H
#415
0H
#416
b11001100 @
1H
#417
0H
#418
b11001101 @
1H
#419
0H
#420
b11001110 @
1H
#421
0H
#422
b11001111 @
1H
#423
0H
#424
b11010000 @
1H
#425
0H
#426
b11010001 @
1H
#427
0H
#428
b11010010 @
1H
#429
0H
#430
b11010011 @
1H
#431
0H
#432
b11010100 @
1H
#433
0H
#434
b11010101 @
1H
#435
0H
#436
b11010110 @
1H
#437
0H
#438
b11010111 @
1H
#439
0H
#440
b11011000 @
1H
#441
0H
#442
b11011001 @
1H
#443
0H
#444
b11011010 @
1H
#445
0H
#446
b11011011 @
1H
#447
0H
#448
b11011100 @
1H
#449
0H
#450
b11011101 @
1H
#451
0H
#452
b11011110 @
1H
#453
0H
#454
b11011111 @
1H
#455
0H
#456
b11100000 @
1H
#457
0H
#458
b11100001 @
1H
#459
0H
#460
b11100010 @
1H
#461
0H
#462
b11100011 @
1H
#463
0H
#464
b11100100 @
1H
#465
0H
#466
b11100101 @
1H
#467
0H
#468
b11100110 @
1H
#469
0H
#470
b11100111 @
1H
#471
0H
#472
b11101000 @
1H
#473
0H
#474
b11101001 @
1H
#475
0H
#476
b11101010 @
1H
#477
0H
#478
b11101011 @
1H
#479
0H
#480
b11101100 @
1H
#481
0H
#482
b11101101 @
1H
#483
0H
#484
b11101110 @
1H
#485
0H
#486
b11101111 @
1H
#487
0H
#488
b11110000 @
1H
#489
0H
#490
b11110001 @
1H
#491
0H
#492
b11110010 @
1H
#493
0H
#494
b11110011 @
1H
#495
0H
#496
b11110100 @
1H
#497
0H
#498
b11110101 @
1H
#499
0H
#500
b11110110 @
1H
#501
0H
#502
b11110111 @
1H
#503
0H
#504
b11111000 @
1H
#505
0H
#506
b11111001 @
1H
#507
0H
#508
b11111010 @
1H
#509
0H
#510
b11111011 @
1H
#511
0H
#512
b11111100 @
1H
#513
0H
#514
b11111101 @
1H
#515
0H
#516
b11111110 @
1H
#517
0H
#518
b11111111 @
1H
#519
0H
#520
b00000000000000000000000000001001 <
1?
b00000000 @
1H
#521
0H
#522
b00000000000000000000000000001001 =
0?
b00000001 @
1H
#523
0H
#524
b00000010 @
1H
#525
0H
#526
b00000011 @
1H
#527
0H
#528
b00000100 @
1H
#529
0H
#530
b00000101 @
1H
#531
0H
#532
b00000110 @
1H
#533
0H
#534
b00000111 @
1H
#535
0H
#536
b00001000 @
1H
#537
0H
#538
b00001001 @
1H
#539
0H
#540
b00001010 @
1H
#541
0H
#542
b00001011 @
1H
#543
0H
#544
b00001100 @
1H
#545
0H
#546
b00001101 @
1H
#547
0H
#548
b00001110 @
1H
#549
0H
#550
b00001111 @
1H
#551
0H
#552
b00010000 @
1H
#553
0H
#554
b00010001 @
1H
#555
0H
#556
b00010010 @
1H
#557
0H
#558
b00010011 @
1H
#559
0H
#560
b00010100 @
1H
#561
0H
#562
b00010101 @
1H
#563
0H
#564
b00010110 @
1H
#565
0H
#566
b00010111 @
1H
#567
0H
#568
b00011000 @
1H
#569
0H
